tccbox-2025.6.6.data/purelib/tccbox/__init__.py
tccbox-2025.6.6.data/purelib/tccbox/__main__.py
tccbox-2025.6.6.data/purelib/tccbox/tcc_dist/bin/tcc
tccbox-2025.6.6.data/purelib/tccbox/tcc_dist/include/libtcc.h
tccbox-2025.6.6.data/purelib/tccbox/tcc_dist/lib/libtcc.a
tccbox-2025.6.6.data/purelib/tccbox/tcc_dist/lib/libtcc.dylib
tccbox-2025.6.6.data/purelib/tccbox/tcc_dist/lib/tcc/bcheck.o
tccbox-2025.6.6.data/purelib/tccbox/tcc_dist/lib/tcc/bt-exe.o
tccbox-2025.6.6.data/purelib/tccbox/tcc_dist/lib/tcc/bt-log.o
tccbox-2025.6.6.data/purelib/tccbox/tcc_dist/lib/tcc/libtcc1.a
tccbox-2025.6.6.data/purelib/tccbox/tcc_dist/lib/tcc/runmain.o
tccbox-2025.6.6.data/purelib/tccbox/tcc_dist/lib/tcc/include/float.h
tccbox-2025.6.6.data/purelib/tccbox/tcc_dist/lib/tcc/include/stdalign.h
tccbox-2025.6.6.data/purelib/tccbox/tcc_dist/lib/tcc/include/stdarg.h
tccbox-2025.6.6.data/purelib/tccbox/tcc_dist/lib/tcc/include/stdatomic.h
tccbox-2025.6.6.data/purelib/tccbox/tcc_dist/lib/tcc/include/stdbool.h
tccbox-2025.6.6.data/purelib/tccbox/tcc_dist/lib/tcc/include/stddef.h
tccbox-2025.6.6.data/purelib/tccbox/tcc_dist/lib/tcc/include/stdnoreturn.h
tccbox-2025.6.6.data/purelib/tccbox/tcc_dist/lib/tcc/include/tccdefs.h
tccbox-2025.6.6.data/purelib/tccbox/tcc_dist/lib/tcc/include/tcclib.h
tccbox-2025.6.6.data/purelib/tccbox/tcc_dist/lib/tcc/include/tgmath.h
tccbox-2025.6.6.data/purelib/tccbox/tcc_dist/lib/tcc/include/varargs.h
tccbox-2025.6.6.data/purelib/tccbox/tcc_dist/share/man/man1/tcc.1
tccbox-2025.6.6.dist-info/METADATA
tccbox-2025.6.6.dist-info/WHEEL
tccbox-2025.6.6.dist-info/top_level.txt
tccbox-2025.6.6.dist-info/RECORD
