Metadata-Version: 2.4
Name: tccbox
Version: 2025.6.6
Summary: tccbox: pack platform specific tiny c compiler
Home-page: https://github.com/metab0t/tccbox
Author: Yue Yang
Author-email: metab0t@outlook.com
License: LGPL
Dynamic: author
Dynamic: author-email
Dynamic: description
Dynamic: description-content-type
Dynamic: home-page
Dynamic: license
Dynamic: summary
